CHANGES.txt
LICENSE.txt
MANIFEST.in
README.rst
setup.py
src/doublespeak/__init__.py
src/doublespeak/message.py
src/doublespeak.egg-info/PKG-INFO
src/doublespeak.egg-info/SOURCES.txt
src/doublespeak.egg-info/dependency_links.txt
src/doublespeak.egg-info/entry_points.txt
src/doublespeak.egg-info/namespace_packages.txt
src/doublespeak.egg-info/not-zip-safe
src/doublespeak.egg-info/requires.txt
src/doublespeak.egg-info/top_level.txt