Metadata-Version: 1.1
Name: doublespeak
Version: 0.3
Summary: Babel/distutils commands to help with managing Javascript translations.
Home-page: https://github.com/minddistrict/doublespeak
Author: Minddistrict
Author-email: UNKNOWN
License: BSD
Keywords: Javascript translations Babel
Platform: UNKNOWN
Classifier: Programming Language :: Python
Classifier: Intended Audience :: Developers
Classifier: License :: OSI Approved :: BSD License
Classifier: Topic :: Software Development :: Internationalization
Classifier: Programming Language :: Python :: 2.7
